rtl/stream_pipeline.sv
module stream_pipeline #(
    parameter int DATA_WIDTH = 32
    // parameter int NUM_STAGES = 1
)(
    input  logic                  clk,
    input  logic                  rst,

    input  logic [DATA_WIDTH-1:0] in_data,
    input  logic                  in_valid,
    output logic                  in_ready,

    output logic [DATA_WIDTH-1:0] out_data,
    output logic                  out_valid,
    input  logic                  out_ready
);
    
    always_ff @(posedge clk) begin
        if (rst) begin
            out_valid <= 0;
            out_data <= 32'b0;
        end else begin
            if (in_valid && in_ready) begin
                out_data <= in_data + 1;
                out_valid <= 1;
            end else if (out_ready && out_valid) begin
                out_valid <= 0;
            end
        end
    end

    assign in_ready = !out_valid || (out_ready && out_valid);

endmodule

trace.vcd
$version Generated by VerilatedVcd $end
$timescale 1ps $end
 $scope module TOP $end
  $var wire 1 # clk $end
  $var wire 1 $ rst $end
  $var wire 32 % in_data [31:0] $end
  $var wire 1 & in_valid $end
  $var wire 1 ' in_ready $end
  $var wire 32 ( out_data [31:0] $end
  $var wire 1 ) out_valid $end
  $var wire 1 * out_ready $end
  $scope module stream_pipeline $end
   $var wire 32 + DATA_WIDTH [31:0] $end
   $var wire 1 # clk $end
   $var wire 1 $ rst $end
   $var wire 32 % in_data [31:0] $end
   $var wire 1 & in_valid $end
   $var wire 1 ' in_ready $end
   $var wire 32 ( out_data [31:0] $end
   $var wire 1 ) out_valid $end
   $var wire 1 * out_ready $end
  $upscope $end
 $upscope $end
$enddefinitions $end


#0
0#
1$
b00000000000000000000000000000000 %
0&
1'
b00000000000000000000000000000000 (
0)
0*
b00000000000000000000000000100000 +
#5
1#
#10
0#
0$
1&
b00000000000000000000000000000001 (
1)
1*
#15
1#
#20
0#
b00000000000000000000000000000010 %
#25
1#
b00000000000000000000000000000011 (
#30
0#
b00000000000000000000000000000011 %
#35
1#
b00000000000000000000000000000100 (
#40
0#
b00000000000000000000000000000100 %
0'
0*
#45
1#
#50
0#
1'
1*
#55
1#
b00000000000000000000000000000101 (
#60
0#
b00000000000000000000000000000110 %
#65
1#
b00000000000000000000000000000111 (
#70
0#
b00000000000000000000000000000111 %
#75
1#
b00000000000000000000000000001000 (
#80
0#
b00000000000000000000000000001000 %
0'
0*
#85
1#
#90
0#
1'
1*
#95
1#
b00000000000000000000000000001001 (
#100
0#
b00000000000000000000000000001010 %
0'
0*
#105
1#
#110
0#
#115
1#
#120
0#
#125
1#
#130
0#
1'
1*
#135
1#
b00000000000000000000000000001011 (
#140
0#
b00000000000000000000000000001110 %
#145
1#
b00000000000000000000000000001111 (
#150
0#
b00000000000000000000000000001111 %
#155
1#
b00000000000000000000000000010000 (
#160
0#
b00000000000000000000000000010000 %
#165
1#
b00000000000000000000000000010001 (
#170
0#
b00000000000000000000000000010001 %
#175
1#
b00000000000000000000000000010010 (
#180
0#
b00000000000000000000000000010010 %
0'
0*
#185
1#
#190
0#
1'
1*
#195
1#
b00000000000000000000000000010011 (
#200
0#
b00000000000000000000000000010100 %
0'
0*
#205
1#
#210
0#
1'
1*
#215
1#
b00000000000000000000000000010101 (
#220
0#
b00000000000000000000000000010110 %
#225
1#
b00000000000000000000000000010111 (
#230
0#
b00000000000000000000000000010111 %
#235
1#
b00000000000000000000000000011000 (
#240
0#
b00000000000000000000000000011000 %
0'
0*
#245
1#
#250
0#
1'
1*
#255
1#
b00000000000000000000000000011001 (
#260
0#
b00000000000000000000000000011010 %
#265
1#
b00000000000000000000000000011011 (
#270
0#
b00000000000000000000000000011011 %
#275
1#
b00000000000000000000000000011100 (
#280
0#
b00000000000000000000000000011100 %
0'
0*
#285
1#
#290
0#
#295
1#
#300
0#
#305
1#
#310
0#
1'
1*
#315
1#
b00000000000000000000000000011101 (
#320
0#
b00000000000000000000000000100000 %
#325
1#
b00000000000000000000000000100001 (
#330
0#
b00000000000000000000000000100001 %
0'
0*
#335
1#
#340
0#
#345
1#
#350
0#
1'
1*
#355
1#
b00000000000000000000000000100010 (
#360
0#
b00000000000000000000000000100100 %
#365
1#
b00000000000000000000000000100101 (
#370
0#
b00000000000000000000000000100101 %
#375
1#
b00000000000000000000000000100110 (
#380
0#
b00000000000000000000000000100110 %
#385
1#
b00000000000000000000000000100111 (
#390
0#
b00000000000000000000000000100111 %
#395
1#
b00000000000000000000000000101000 (
#400
0#
b00000000000000000000000000101000 %
#405
1#
b00000000000000000000000000101001 (
#410
0#
b00000000000000000000000000101001 %
#415
1#
b00000000000000000000000000101010 (
#420
0#
b00000000000000000000000000101010 %
#425
1#
b00000000000000000000000000101011 (
#430
0#
b00000000000000000000000000101011 %
#435
1#
b00000000000000000000000000101100 (
#440
0#
b00000000000000000000000000101100 %
0'
0*
#445
1#
#450
0#
#455
1#
#460
0#
1'
1*
#465
1#
b00000000000000000000000000101101 (
#470
0#
b00000000000000000000000000101111 %
#475
1#
b00000000000000000000000000110000 (
#480
0#
b00000000000000000000000000110000 %
#485
1#
b00000000000000000000000000110001 (
#490
0#
b00000000000000000000000000110001 %
#495
1#
b00000000000000000000000000110010 (
#500
0#
b00000000000000000000000000110010 %
0'
0*
#505
1#
#510
0#
1'
1*
#515
1#
b00000000000000000000000000110011 (
#520
0#
b00000000000000000000000000110100 %
0'
0*
#525
1#
#530
0#
1'
1*
#535
1#
b00000000000000000000000000110101 (
#540
0#
b00000000000000000000000000110110 %
#545
1#
b00000000000000000000000000110111 (
#550
0#
b00000000000000000000000000110111 %
0'
0*
#555
1#
#560
0#
1'
1*
#565
1#
b00000000000000000000000000111000 (
#570
0#
b00000000000000000000000000111001 %
#575
1#
b00000000000000000000000000111010 (
#580
0#
b00000000000000000000000000111010 %
0'
0*
#585
1#
#590
0#
1'
1*
#595
1#
b00000000000000000000000000111011 (
#600
0#
b00000000000000000000000000111100 %
0'
0*
#605
1#
#610
0#
1'
1*
#615
1#
b00000000000000000000000000111101 (
#620
0#
b00000000000000000000000000111110 %
#625
1#
b00000000000000000000000000111111 (
#630
0#
b00000000000000000000000000111111 %
#635
1#
b00000000000000000000000001000000 (
#640
0#
b00000000000000000000000001000000 %
0'
0*
#645
1#
#650
0#
1'
1*
#655
1#
b00000000000000000000000001000001 (
#660
0#
b00000000000000000000000001000010 %
0'
0*
#665
1#
#670
0#
1'
1*
#675
1#
b00000000000000000000000001000011 (
#680
0#
b00000000000000000000000001000100 %
0'
0*
#685
1#
#690
0#
1'
1*
#695
1#
b00000000000000000000000001000101 (
#700
0#
b00000000000000000000000001000110 %
#705
1#
b00000000000000000000000001000111 (
#710
0#
b00000000000000000000000001000111 %
#715
1#
b00000000000000000000000001001000 (
#720
0#
b00000000000000000000000001001000 %
0'
0*
#725
1#
#730
0#
1'
1*
#735
1#
b00000000000000000000000001001001 (
#740
0#
b00000000000000000000000001001010 %
0'
0*
#745
1#
#750
0#
#755
1#
#760
0#
#765
1#
#770
0#
1'
1*
#775
1#
b00000000000000000000000001001011 (
#780
0#
b00000000000000000000000001001110 %
0'
0*
#785
1#
#790
0#
1'
1*
#795
1#
b00000000000000000000000001001111 (
#800
0#
b00000000000000000000000001010000 %
0'
0*
#805
1#
#810
0#
1'
1*
#815
1#
b00000000000000000000000001010001 (
#820
0#
b00000000000000000000000001010010 %
#825
1#
b00000000000000000000000001010011 (
#830
0#
b00000000000000000000000001010011 %
#835
1#
b00000000000000000000000001010100 (
#840
0#
b00000000000000000000000001010100 %
0'
0*
#845
1#
#850
0#
#855
1#
#860
0#
#865
1#
#870
0#
1'
1*
#875
1#
b00000000000000000000000001010101 (
#880
0#
b00000000000000000000000001011000 %
0'
0*
#885
1#
#890
0#
1'
1*
#895
1#
b00000000000000000000000001011001 (
#900
0#
b00000000000000000000000001011010 %
#905
1#
b00000000000000000000000001011011 (
#910
0#
b00000000000000000000000001011011 %
#915
1#
b00000000000000000000000001011100 (
#920
0#
b00000000000000000000000001011100 %
0'
0*
#925
1#
#930
0#
#935
1#
#940
0#
1'
1*
#945
1#
b00000000000000000000000001011101 (
#950
0#
b00000000000000000000000001011111 %
#955
1#
b00000000000000000000000001100000 (
#960
0#
b00000000000000000000000001100000 %
0'
0*
#965
1#
#970
0#
1'
1*
#975
1#
b00000000000000000000000001100001 (
#980
0#
b00000000000000000000000001100010 %
#985
1#
b00000000000000000000000001100011 (
#990
0#
b00000000000000000000000001100011 %
#995
1#
b00000000000000000000000001100100 (
#1000
0#
b00000000000000000000000001100100 %
0'
0*
#1005
1#
#1010
0#
1'
1*
#1015
1#
b00000000000000000000000001100101 (
#1020
0#
b00000000000000000000000001100110 %
0'
0*
#1025
1#
#1030
0#
1'
1*
#1035
1#
b00000000000000000000000001100111 (
#1040
0#
b00000000000000000000000001101000 %
#1045
1#
b00000000000000000000000001101001 (
#1050
0#
b00000000000000000000000001101001 %
#1055
1#
b00000000000000000000000001101010 (
#1060
0#
b00000000000000000000000001101010 %
#1065
1#
b00000000000000000000000001101011 (
#1070
0#
b00000000000000000000000001101011 %
#1075
1#
b00000000000000000000000001101100 (
#1080
0#
b00000000000000000000000001101100 %
#1085
1#
b00000000000000000000000001101101 (
#1090
0#
b00000000000000000000000001101101 %
#1095
1#
b00000000000000000000000001101110 (
#1100
0#
b00000000000000000000000001101110 %
0'
0*
#1105
1#
#1110
0#
1'
1*
#1115
1#
b00000000000000000000000001101111 (
#1120
0#
b00000000000000000000000001110000 %
0'
0*
#1125
1#
#1130
0#
#1135
1#
#1140
0#
#1145
1#
#1150
0#
1'
1*
#1155
1#
b00000000000000000000000001110001 (
#1160
0#
b00000000000000000000000001110100 %
#1165
1#
b00000000000000000000000001110101 (
#1170
0#
b00000000000000000000000001110101 %
#1175
1#
b00000000000000000000000001110110 (
#1180
0#
b00000000000000000000000001110110 %
#1185
1#
b00000000000000000000000001110111 (
#1190
0#
b00000000000000000000000001110111 %
#1195
1#
b00000000000000000000000001111000 (
#1200
0#
b00000000000000000000000001111000 %
0'
0*
#1205
1#
#1210
0#
1'
1*
#1215
1#
b00000000000000000000000001111001 (
#1220
0#
b00000000000000000000000001111010 %
#1225
1#
b00000000000000000000000001111011 (
#1230
0#
b00000000000000000000000001111011 %
#1235
1#
b00000000000000000000000001111100 (
#1240
0#
b00000000000000000000000001111100 %
0'
0*
#1245
1#
#1250
0#
1'
1*
#1255
1#
b00000000000000000000000001111101 (
#1260
0#
b00000000000000000000000001111110 %
#1265
1#
b00000000000000000000000001111111 (
#1270
0#
b00000000000000000000000001111111 %
0'
0*
#1275
1#
#1280
0#
#1285
1#
#1290
0#
#1295
1#
#1300
0#
1'
1*
#1305
1#
b00000000000000000000000010000000 (
#1310
0#
b00000000000000000000000010000011 %
0'
0*
#1315
1#
#1320
0#
#1325
1#
#1330
0#
1'
1*
#1335
1#
b00000000000000000000000010000100 (
#1340
0#
b00000000000000000000000010000110 %
#1345
1#
b00000000000000000000000010000111 (
#1350
0#
b00000000000000000000000010000111 %
#1355
1#
b00000000000000000000000010001000 (
#1360
0#
b00000000000000000000000010001000 %
0'
0*
#1365
1#
#1370
0#
1'
1*
#1375
1#
b00000000000000000000000010001001 (
#1380
0#
b00000000000000000000000010001010 %
0'
0*
#1385
1#
#1390
0#
1'
1*
#1395
1#
b00000000000000000000000010001011 (
#1400
0#
b00000000000000000000000010001100 %
0'
0*
#1405
1#
#1410
0#
1'
1*
#1415
1#
b00000000000000000000000010001101 (
#1420
0#
b00000000000000000000000010001110 %
#1425
1#
b00000000000000000000000010001111 (
#1430
0#
b00000000000000000000000010001111 %
#1435
1#
b00000000000000000000000010010000 (
#1440
0#
b00000000000000000000000010010000 %
0'
0*
#1445
1#
#1450
0#
#1455
1#
#1460
0#
#1465
1#
#1470
0#
1'
1*
#1475
1#
b00000000000000000000000010010001 (
#1480
0#
b00000000000000000000000010010100 %
0'
0*
#1485
1#
#1490
0#
1'
1*
#1495
1#
b00000000000000000000000010010101 (
#1500
0#
b00000000000000000000000010010110 %
0'
0*
#1505
1#
#1510
0#
1'
1*
#1515
1#
b00000000000000000000000010010111 (
#1520
0#
b00000000000000000000000010011000 %
0'
0*
#1525
1#
#1530
0#
1'
1*
#1535
1#
b00000000000000000000000010011001 (
#1540
0#
b00000000000000000000000010011010 %
#1545
1#
b00000000000000000000000010011011 (
#1550
0#
b00000000000000000000000010011011 %
#1555
1#
b00000000000000000000000010011100 (
#1560
0#
b00000000000000000000000010011100 %
#1565
1#
b00000000000000000000000010011101 (
#1570
0#
b00000000000000000000000010011101 %
0'
0*
#1575
1#
#1580
0#
#1585
1#
#1590
0#
1'
1*
#1595
1#
b00000000000000000000000010011110 (
#1600
0#
b00000000000000000000000010100000 %
0'
0*
#1605
1#
#1610
0#
1'
1*
#1615
1#
b00000000000000000000000010100001 (
#1620
0#
b00000000000000000000000010100010 %
#1625
1#
b00000000000000000000000010100011 (
#1630
0#
b00000000000000000000000010100011 %
0'
0*
#1635
1#
#1640
0#
#1645
1#
#1650
0#
#1655
1#
#1660
0#
#1665
1#
#1670
0#
1'
1*
#1675
1#
b00000000000000000000000010100100 (
#1680
0#
b00000000000000000000000010101000 %
0'
0*
#1685
1#
#1690
0#
1'
1*
#1695
1#
b00000000000000000000000010101001 (
#1700
0#
b00000000000000000000000010101010 %
0'
0*
#1705
1#
#1710
0#
1'
1*
#1715
1#
b00000000000000000000000010101011 (
#1720
0#
b00000000000000000000000010101100 %
0'
0*
#1725
1#
#1730
0#
1'
1*
#1735
1#
b00000000000000000000000010101101 (
#1740
0#
b00000000000000000000000010101110 %
#1745
1#
b00000000000000000000000010101111 (
#1750
0#
b00000000000000000000000010101111 %
0'
0*
#1755
1#
#1760
0#
#1765
1#
#1770
0#
1'
1*
#1775
1#
b00000000000000000000000010110000 (
#1780
0#
b00000000000000000000000010110010 %
#1785
1#
b00000000000000000000000010110011 (
#1790
0#
b00000000000000000000000010110011 %
#1795
1#
b00000000000000000000000010110100 (
#1800
0#
b00000000000000000000000010110100 %
0'
0*
#1805
1#
#1810
0#
1'
1*
#1815
1#
b00000000000000000000000010110101 (
#1820
0#
b00000000000000000000000010110110 %
#1825
1#
b00000000000000000000000010110111 (
#1830
0#
b00000000000000000000000010110111 %
#1835
1#
b00000000000000000000000010111000 (
#1840
0#
b00000000000000000000000010111000 %
#1845
1#
b00000000000000000000000010111001 (
#1850
0#
b00000000000000000000000010111001 %
0'
0*
#1855
1#
#1860
0#
#1865
1#
#1870
0#
#1875
1#
#1880
0#
#1885
1#
#1890
0#
#1895
1#
#1900
0#
#1905
1#
#1910
0#
1'
1*
#1915
1#
b00000000000000000000000010111010 (
#1920
0#
b00000000000000000000000011000000 %
0'
0*
#1925
1#
#1930
0#
#1935
1#
#1940
0#
#1945
1#
#1950
0#
#1955
1#
#1960
0#
1'
1*
#1965
1#
b00000000000000000000000011000001 (
#1970
0#
b00000000000000000000000011000101 %
#1975
1#
b00000000000000000000000011000110 (
#1980
0#
b00000000000000000000000011000110 %
#1985
1#
b00000000000000000000000011000111 (
#1990
0#
b00000000000000000000000011000111 %
#1995
1#
b00000000000000000000000011001000 (
#2000
0#
b00000000000000000000000011001000 %
0'
0*
#2005
1#
#2010
0#
#2015
1#
#2020
0#
1'
1*
#2025
1#
b00000000000000000000000011001001 (
#2030
0#
b00000000000000000000000011001011 %
#2035
1#
b00000000000000000000000011001100 (
#2040
0#
b00000000000000000000000011001100 %
0'
0*
#2045
1#
#2050
0#
#2055
1#
#2060
0#
#2065
1#
#2070
0#
1'
1*
#2075
1#
b00000000000000000000000011001101 (
#2080
0#
b00000000000000000000000011010000 %
#2085
1#
b00000000000000000000000011010001 (
#2090
0#
b00000000000000000000000011010001 %
#2095
1#
b00000000000000000000000011010010 (
#2100
0#
b00000000000000000000000011010010 %
#2105
1#
b00000000000000000000000011010011 (
#2110
0#
b00000000000000000000000011010011 %
#2115
1#
b00000000000000000000000011010100 (
#2120
0#
b00000000000000000000000011010100 %
0'
0*
#2125
1#
#2130
0#
#2135
1#
#2140
0#
1'
1*
#2145
1#
b00000000000000000000000011010101 (
#2150
0#
b00000000000000000000000011010111 %
#2155
1#
b00000000000000000000000011011000 (
#2160
0#
b00000000000000000000000011011000 %
0'
0*
#2165
1#
#2170
0#
1'
1*
#2175
1#
b00000000000000000000000011011001 (
#2180
0#
b00000000000000000000000011011010 %
0'
0*
#2185
1#
#2190
0#
#2195
1#
#2200
0#
#2205
1#
#2210
0#
1'
1*
#2215
1#
b00000000000000000000000011011011 (
#2220
0#
b00000000000000000000000011011110 %
0'
0*
#2225
1#
#2230
0#
1'
1*
#2235
1#
b00000000000000000000000011011111 (
#2240
0#
b00000000000000000000000011100000 %
#2245
1#
b00000000000000000000000011100001 (
#2250
0#
b00000000000000000000000011100001 %
0'
0*
#2255
1#
#2260
0#
1'
1*
#2265
1#
b00000000000000000000000011100010 (
#2270
0#
b00000000000000000000000011100011 %
#2275
1#
b00000000000000000000000011100100 (
#2280
0#
b00000000000000000000000011100100 %
0'
0*
#2285
1#
#2290
0#
1'
1*
#2295
1#
b00000000000000000000000011100101 (
#2300
0#
b00000000000000000000000011100110 %
#2305
1#
b00000000000000000000000011100111 (
#2310
0#
b00000000000000000000000011100111 %
0'
0*
#2315
1#
#2320
0#
1'
1*
#2325
1#
b00000000000000000000000011101000 (
#2330
0#
b00000000000000000000000011101001 %
#2335
1#
b00000000000000000000000011101010 (
#2340
0#
b00000000000000000000000011101010 %
0'
0*
#2345
1#
#2350
0#
#2355
1#
#2360
0#
1'
1*
#2365
1#
b00000000000000000000000011101011 (
#2370
0#
b00000000000000000000000011101101 %
0'
0*
#2375
1#
#2380
0#
1'
1*
#2385
1#
b00000000000000000000000011101110 (
#2390
0#
b00000000000000000000000011101111 %
#2395
1#
b00000000000000000000000011110000 (
#2400
0#
b00000000000000000000000011110000 %
0'
0*
#2405
1#
#2410
0#
#2415
1#
#2420
0#
#2425
1#
#2430
0#
1'
1*
#2435
1#
b00000000000000000000000011110001 (
#2440
0#
b00000000000000000000000011110100 %
0'
0*
#2445
1#
#2450
0#
1'
1*
#2455
1#
b00000000000000000000000011110101 (
#2460
0#
b00000000000000000000000011110110 %
0'
0*
#2465
1#
#2470
0#
1'
1*
#2475
1#
b00000000000000000000000011110111 (
#2480
0#
b00000000000000000000000011111000 %
#2485
1#
b00000000000000000000000011111001 (
#2490
0#
b00000000000000000000000011111001 %
#2495
1#
b00000000000000000000000011111010 (
#2500
0#
b00000000000000000000000011111010 %
0'
0*
#2505
1#
#2510
0#
1'
1*
#2515
1#
b00000000000000000000000011111011 (
#2520
0#
b00000000000000000000000011111100 %
0'
0*
#2525
1#
#2530
0#
1'
1*
#2535
1#
b00000000000000000000000011111101 (
#2540
0#
b00000000000000000000000011111110 %
0'
0*
#2545
1#
#2550
0#
#2555
1#
#2560
0#
#2565
1#
#2570
0#
1'
1*
#2575
1#
b00000000000000000000000011111111 (
#2580
0#
b00000000000000000000000100000010 %
0'
0*
#2585
1#
#2590
0#
1'
1*
#2595
1#
b00000000000000000000000100000011 (
#2600
0#
b00000000000000000000000100000100 %
0'
0*
#2605
1#
#2610
0#
#2615
1#
#2620
0#
1'
1*
#2625
1#
b00000000000000000000000100000101 (
#2630
0#
b00000000000000000000000100000111 %
0'
0*
#2635
1#
#2640
0#
1'
1*
#2645
1#
b00000000000000000000000100001000 (
#2650
0#
b00000000000000000000000100001001 %
#2655
1#
b00000000000000000000000100001010 (
#2660
0#
b00000000000000000000000100001010 %
#2665
1#
b00000000000000000000000100001011 (
#2670
0#
b00000000000000000000000100001011 %
0'
0*
#2675
1#
#2680
0#
1'
1*
#2685
1#
b00000000000000000000000100001100 (
#2690
0#
b00000000000000000000000100001101 %
0'
0*
#2695
1#
#2700
0#
#2705
1#
#2710
0#
#2715
1#
#2720
0#
#2725
1#
#2730
0#
1'
1*
#2735
1#
b00000000000000000000000100001110 (
#2740
0#
b00000000000000000000000100010010 %
#2745
1#
b00000000000000000000000100010011 (
#2750
0#
b00000000000000000000000100010011 %
#2755
1#
b00000000000000000000000100010100 (
#2760
0#
b00000000000000000000000100010100 %
0'
0*
#2765
1#
#2770
0#
1'
1*
#2775
1#
b00000000000000000000000100010101 (
#2780
0#
b00000000000000000000000100010110 %
0'
0*
#2785
1#
#2790
0#
#2795
1#
#2800
0#
#2805
1#
#2810
0#
1'
1*
#2815
1#
b00000000000000000000000100010111 (
#2820
0#
b00000000000000000000000100011010 %
#2825
1#
b00000000000000000000000100011011 (
#2830
0#
b00000000000000000000000100011011 %
#2835
1#
b00000000000000000000000100011100 (
#2840
0#
b00000000000000000000000100011100 %
#2845
1#
b00000000000000000000000100011101 (
#2850
0#
b00000000000000000000000100011101 %
#2855
1#
b00000000000000000000000100011110 (
#2860
0#
b00000000000000000000000100011110 %
#2865
1#
b00000000000000000000000100011111 (
#2870
0#
b00000000000000000000000100011111 %
0'
0*
#2875
1#
#2880
0#
#2885
1#
#2890
0#
1'
1*
#2895
1#
b00000000000000000000000100100000 (
#2900
0#
b00000000000000000000000100100010 %
0'
0*
#2905
1#
#2910
0#
1'
1*
#2915
1#
b00000000000000000000000100100011 (
#2920
0#
b00000000000000000000000100100100 %
0'
0*
#2925
1#
#2930
0#
1'
1*
#2935
1#
b00000000000000000000000100100101 (
#2940
0#
b00000000000000000000000100100110 %
0'
0*
#2945
1#
#2950
0#
1'
1*
#2955
1#
b00000000000000000000000100100111 (
#2960
0#
b00000000000000000000000100101000 %
0'
0*
#2965
1#
#2970
0#
#2975
1#
#2980
0#
#2985
1#
#2990
0#
1'
1*
#2995
1#
b00000000000000000000000100101001 (
#3000
0#
b00000000000000000000000100101100 %
0'
0*
#3005
1#
#3010
0#
1'
1*
#3015
1#
b00000000000000000000000100101101 (
#3020
0#
b00000000000000000000000100101110 %
0'
0*
#3025
1#
#3030
0#
1'
1*
#3035
1#
b00000000000000000000000100101111 (
#3040
0#
b00000000000000000000000100110000 %
0'
0*
#3045
1#
#3050
0#
#3055
1#
#3060
0#
#3065
1#
#3070
0#
#3075
1#
#3080
0#
#3085
1#
#3090
0#
1'
1*
#3095
1#
b00000000000000000000000100110001 (
#3100
0#
b00000000000000000000000100110110 %
0'
0*
#3105
1#
#3110
0#
1'
1*
#3115
1#
b00000000000000000000000100110111 (
#3120
0#
b00000000000000000000000100111000 %
0'
0*
#3125
1#
#3130
0#
1'
1*
#3135
1#
b00000000000000000000000100111001 (
#3140
0#
b00000000000000000000000100111010 %
#3145
1#
b00000000000000000000000100111011 (
#3150
0#
b00000000000000000000000100111011 %
#3155
1#
b00000000000000000000000100111100 (
#3160
0#
b00000000000000000000000100111100 %
#3165
1#
b00000000000000000000000100111101 (
#3170
0#
b00000000000000000000000100111101 %
#3175
1#
b00000000000000000000000100111110 (
#3180
0#
b00000000000000000000000100111110 %
#3185
1#
b00000000000000000000000100111111 (
#3190
0#
b00000000000000000000000100111111 %
#3195
1#
b00000000000000000000000101000000 (
#3200
0#
b00000000000000000000000101000000 %
0'
0*
#3205
1#
#3210
0#
#3215
1#
#3220
0#
1'
1*
#3225
1#
b00000000000000000000000101000001 (
#3230
0#
b00000000000000000000000101000011 %
#3235
1#
b00000000000000000000000101000100 (
#3240
0#
b00000000000000000000000101000100 %
0'
0*
#3245
1#
#3250
0#
1'
1*
#3255
1#
b00000000000000000000000101000101 (
#3260
0#
b00000000000000000000000101000110 %
#3265
1#
b00000000000000000000000101000111 (
#3270
0#
b00000000000000000000000101000111 %
0'
0*
#3275
1#
#3280
0#
#3285
1#
#3290
0#
1'
1*
#3295
1#
b00000000000000000000000101001000 (
#3300
0#
b00000000000000000000000101001010 %
0'
0*
#3305
1#
#3310
0#
1'
1*
#3315
1#
b00000000000000000000000101001011 (
#3320
0#
b00000000000000000000000101001100 %
#3325
1#
b00000000000000000000000101001101 (
#3330
0#
b00000000000000000000000101001101 %
#3335
1#
b00000000000000000000000101001110 (
#3340
0#
b00000000000000000000000101001110 %
#3345
1#
b00000000000000000000000101001111 (
#3350
0#
b00000000000000000000000101001111 %
0'
0*
#3355
1#
#3360
0#
1'
1*
#3365
1#
b00000000000000000000000101010000 (
#3370
0#
b00000000000000000000000101010001 %
0'
0*
#3375
1#
#3380
0#
#3385
1#
#3390
0#
#3395
1#
#3400
0#
#3405
1#
#3410
0#
#3415
1#
#3420
0#
#3425
1#
#3430
0#
1'
1*
#3435
1#
b00000000000000000000000101010010 (
#3440
0#
b00000000000000000000000101011000 %
#3445
1#
b00000000000000000000000101011001 (
#3450
0#
b00000000000000000000000101011001 %
#3455
1#
b00000000000000000000000101011010 (
#3460
0#
b00000000000000000000000101011010 %
0'
0*
#3465
1#
#3470
0#
1'
1*
#3475
1#
b00000000000000000000000101011011 (
#3480
0#
b00000000000000000000000101011100 %
0'
0*
#3485
1#
#3490
0#
1'
1*
#3495
1#
b00000000000000000000000101011101 (
#3500
0#
b00000000000000000000000101011110 %
#3505
1#
b00000000000000000000000101011111 (
#3510
0#
b00000000000000000000000101011111 %
#3515
1#
b00000000000000000000000101100000 (
#3520
0#
b00000000000000000000000101100000 %
0'
0*
#3525
1#
#3530
0#
#3535
1#
#3540
0#
1'
1*
#3545
1#
b00000000000000000000000101100001 (
#3550
0#
b00000000000000000000000101100011 %
#3555
1#
b00000000000000000000000101100100 (
#3560
0#
b00000000000000000000000101100100 %
#3565
1#
b00000000000000000000000101100101 (
#3570
0#
b00000000000000000000000101100101 %
0'
0*
#3575
1#
#3580
0#
1'
1*
#3585
1#
b00000000000000000000000101100110 (
#3590
0#
b00000000000000000000000101100111 %
0'
0*
#3595
1#
#3600
0#
#3605
1#
#3610
0#
1'
1*
#3615
1#
b00000000000000000000000101101000 (
#3620
0#
b00000000000000000000000101101010 %
#3625
1#
b00000000000000000000000101101011 (
#3630
0#
b00000000000000000000000101101011 %
#3635
1#
b00000000000000000000000101101100 (
#3640
0#
b00000000000000000000000101101100 %
#3645
1#
b00000000000000000000000101101101 (
#3650
0#
b00000000000000000000000101101101 %
#3655
1#
b00000000000000000000000101101110 (
#3660
0#
b00000000000000000000000101101110 %
0'
0*
#3665
1#
#3670
0#
1'
1*
#3675
1#
b00000000000000000000000101101111 (
#3680
0#
b00000000000000000000000101110000 %
0'
0*
#3685
1#
#3690
0#
1'
1*
#3695
1#
b00000000000000000000000101110001 (
#3700
0#
b00000000000000000000000101110010 %
#3705
1#
b00000000000000000000000101110011 (
#3710
0#
b00000000000000000000000101110011 %
#3715
1#
b00000000000000000000000101110100 (
#3720
0#
b00000000000000000000000101110100 %
0'
0*
#3725
1#
#3730
0#
#3735
1#
#3740
0#
1'
1*
#3745
1#
b00000000000000000000000101110101 (
#3750
0#
b00000000000000000000000101110111 %
0'
0*
#3755
1#
#3760
0#
#3765
1#
#3770
0#
#3775
1#
#3780
0#
1'
1*
#3785
1#
b00000000000000000000000101111000 (
#3790
0#
b00000000000000000000000101111011 %
#3795
1#
b00000000000000000000000101111100 (
#3800
0#
b00000000000000000000000101111100 %
0'
0*
#3805
1#
#3810
0#
1'
1*
#3815
1#
b00000000000000000000000101111101 (
#3820
0#
b00000000000000000000000101111110 %
#3825
1#
b00000000000000000000000101111111 (
#3830
0#
b00000000000000000000000101111111 %
0'
0*
#3835
1#
#3840
0#
#3845
1#
#3850
0#
1'
1*
#3855
1#
b00000000000000000000000110000000 (
#3860
0#
b00000000000000000000000110000010 %
0'
0*
#3865
1#
#3870
0#
1'
1*
#3875
1#
b00000000000000000000000110000011 (
#3880
0#
b00000000000000000000000110000100 %
0'
0*
#3885
1#
#3890
0#
#3895
1#
#3900
0#
1'
1*
#3905
1#
b00000000000000000000000110000101 (
#3910
0#
b00000000000000000000000110000111 %
#3915
1#
b00000000000000000000000110001000 (
#3920
0#
b00000000000000000000000110001000 %
0'
0*
#3925
1#
#3930
0#
1'
1*
#3935
1#
b00000000000000000000000110001001 (
#3940
0#
b00000000000000000000000110001010 %
0'
0*
#3945
1#
#3950
0#
#3955
1#
#3960
0#
#3965
1#
#3970
0#
1'
1*
#3975
1#
b00000000000000000000000110001011 (
#3980
0#
b00000000000000000000000110001110 %
#3985
1#
b00000000000000000000000110001111 (
#3990
0#
b00000000000000000000000110001111 %
#3995
1#
b00000000000000000000000110010000 (
#4000
0#
b00000000000000000000000110010000 %
0'
0*
#4005
1#
#4010
0#
1'
1*
#4015
1#
b00000000000000000000000110010001 (
#4020
0#
b00000000000000000000000110010010 %
#4025
1#
b00000000000000000000000110010011 (
#4030
0#
b00000000000000000000000110010011 %
#4035
1#
b00000000000000000000000110010100 (
#4040
0#
b00000000000000000000000110010100 %
0'
0*
#4045
1#
#4050
0#
#4055
1#
#4060
0#
1'
1*
#4065
1#
b00000000000000000000000110010101 (
#4070
0#
b00000000000000000000000110010111 %
0'
0*
#4075
1#
#4080
0#
#4085
1#
#4090
0#
1'
1*
#4095
1#
b00000000000000000000000110011000 (
#4100
0#
b00000000000000000000000110011010 %
0'
0*
#4105
1#
#4110
0#
1'
1*
#4115
1#
b00000000000000000000000110011011 (
#4120
0#
b00000000000000000000000110011100 %
#4125
1#
b00000000000000000000000110011101 (
#4130
0#
b00000000000000000000000110011101 %
#4135
1#
b00000000000000000000000110011110 (
#4140
0#
b00000000000000000000000110011110 %
0'
0*
#4145
1#
#4150
0#
#4155
1#
#4160
0#
#4165
1#
#4170
0#
1'
1*
#4175
1#
b00000000000000000000000110011111 (
#4180
0#
b00000000000000000000000110100010 %
0'
0*
#4185
1#
#4190
0#
1'
1*
#4195
1#
b00000000000000000000000110100011 (
#4200
0#
b00000000000000000000000110100100 %
0'
0*
#4205
1#
#4210
0#
1'
1*
#4215
1#
b00000000000000000000000110100101 (
#4220
0#
b00000000000000000000000110100110 %
0'
0*
#4225
1#
#4230
0#
1'
1*
#4235
1#
b00000000000000000000000110100111 (
#4240
0#
b00000000000000000000000110101000 %
#4245
1#
b00000000000000000000000110101001 (
